ghostscript/__init__.py
ghostscript/_errors.py
ghostscript/_gsprint.py
ghostscript-0.8.dist-info/licenses/COPYING
ghostscript-0.8.dist-info/METADATA
ghostscript-0.8.dist-info/WHEEL
ghostscript-0.8.dist-info/top_level.txt
ghostscript-0.8.dist-info/zip-safe
ghostscript-0.8.dist-info/RECORD
