Metadata-Version: 2.4
Name: ghostscript
Version: 0.8
Summary: Interface to the Ghostscript C-API, both high- and low-level, based on ctypes
Home-page: https://gitlab.com/pdftools/python-ghostscript
Download-URL: https://pypi.python.org/pypi/ghostscript
Author: Hartmut Goebel
Author-email: h.goebel@crazy-compilers.com
License: GPL-3.0-or-later
Keywords: Ghostscript,PDF,Postscript
Classifier: Development Status :: 5 - Production/Stable
Classifier: Intended Audience :: Developers
Classifier: Natural Language :: English
Classifier: Operating System :: OS Independent
Classifier: Programming Language :: Python
Classifier: Programming Language :: Python :: 3
Classifier: Programming Language :: Python :: 3.6
Classifier: Programming Language :: Python :: 3.7
Classifier: Programming Language :: Python :: 3.8
Classifier: Programming Language :: Python :: 3.9
Classifier: Programming Language :: Python :: 3.10
Classifier: Programming Language :: Python :: 3.11
Classifier: Programming Language :: Python :: 3.12
Classifier: Programming Language :: Python :: 3.13
Classifier: Topic :: Software Development :: Libraries :: Python Modules
License-File: COPYING
Dynamic: download-url
Dynamic: license-file
